MANIFEST.in
README.rst
setup.cfg
setup.py
versioneer.py
smartcard/app/openpgp/__init__.py
smartcard/app/openpgp/_version.py
smartcard/app/openpgp/tag.py
smartcard/app/openpgp/cli/simple.py
smartcard/app/openpgp/cli/test.py
smartcard/app/openpgp/cli/randpin/epaper.py
smartcard/app/openpgp/cli/randpin/framebuffer.py
smartcard/app/openpgp/cli/randpin/waveshare_epaper.py
smartcard_app_openpgp.egg-info/PKG-INFO
smartcard_app_openpgp.egg-info/SOURCES.txt
smartcard_app_openpgp.egg-info/dependency_links.txt
smartcard_app_openpgp.egg-info/entry_points.txt
smartcard_app_openpgp.egg-info/requires.txt
smartcard_app_openpgp.egg-info/top_level.txt