Metadata-Version: 2.1
Name: smartcard-app-openpgp
Version: 0.4.0
Summary: OpenPGP smartcard application implementation.
Home-page: http://github.com/vpelletier/python-smartcard-app-openpgp
Author: Vincent Pelletier
Author-email: plr.vincent@gmail.com
License: GPLv3+
Keywords: smartcard openpgp
Platform: any
Classifier: License :: OSI Approved :: GNU General Public License v3 or later (GPLv3+)
Classifier: Operating System :: OS Independent
Classifier: Programming Language :: Python :: 3
Classifier: Programming Language :: Python :: Implementation :: CPython
Classifier: Programming Language :: Python :: Implementation :: PyPy
Classifier: Topic :: Security :: Cryptography
Provides-Extra: ccid
Provides-Extra: randpin
